gopikachu/__init__.py
gopikachu/ALL_PRACT_EASY/P1.py
gopikachu/ALL_PRACT_EASY/P10.py
gopikachu/ALL_PRACT_EASY/P11.py
gopikachu/ALL_PRACT_EASY/P12.py
gopikachu/ALL_PRACT_EASY/P2.py
gopikachu/ALL_PRACT_EASY/P3.py
gopikachu/ALL_PRACT_EASY/P4.py
gopikachu/ALL_PRACT_EASY/P5.py
gopikachu/ALL_PRACT_EASY/P7.py
gopikachu/ALL_PRACT_EASY/P8.py
gopikachu/ALL_PRACT_EASY/P9.py
gopikachu/ALL_PRACT_EASY/p6.py
gopikachu/ALL_PRACT_PROPER/PRACTICAL_NO_01_new[1].pdf
gopikachu/ALL_PRACT_PROPER/PRACTICAL_NO_02_new[1].pdf
gopikachu/ALL_PRACT_PROPER/PRACTICAL_NO_03_-_new[1].pdf
gopikachu/ALL_PRACT_PROPER/PRACTICAL_NO_04_-_new[1].pdf
gopikachu/ALL_PRACT_PROPER/PRACTICAL_NO_05_new[1].pdf
gopikachu/ALL_PRACT_PROPER/PRACTICAL_NO_06_new[1].pdf
gopikachu/ALL_PRACT_PROPER/PRACTICAL_NO_07_new[1].pdf
gopikachu/ALL_PRACT_PROPER/PRACTICAL_NO_08[2].pdf
gopikachu/ALL_PRACT_PROPER/PRACTICAL_NO_09[2].pdf
gopikachu/ALL_PRACT_PROPER/PRACTICAL_NO_10[1].pdf
gopikachu/GUIDE/HELPCON.pdf
gopikachu-0.1.dist-info/LICENSE
gopikachu-0.1.dist-info/METADATA
gopikachu-0.1.dist-info/WHEEL
gopikachu-0.1.dist-info/top_level.txt
gopikachu-0.1.dist-info/RECORD
